{
  "camera_models": [
    {
      "id": "polaroid_sx70",
      "name": "SX-70",
      "brand": "Polaroid",
      "model": "SX-70",
      "specific_model": "Original",
      "capacity": 10,
      "default_image": "camera.aperture",
      "default_icon": "camera.aperture",
      "year_introduced": 1972,
      "film_type": "SX-70"
    },
    {
      "id": "polaroid_sx70_alpha",
      "name": "SX-70 Alpha",
      "brand": "Polaroid",
      "model": "SX-70",
      "specific_model": "Alpha",
      "capacity": 10,
      "default_image": "camera.aperture",
      "default_icon": "camera.aperture",
      "year_introduced": 1974,
      "film_type": "SX-70"
    },
    {
      "id": "polaroid_sx70_sonar",
      "name": "SX-70 Sonar",
      "brand": "Polaroid",
      "model": "SX-70",
      "specific_model": "Sonar",
      "capacity": 10,
      "default_image": "camera.aperture",
      "default_icon": "camera.aperture",
      "year_introduced": 1978,
      "film_type": "SX-70"
    },
    {
      "id": "polaroid_sx70_model2",
      "name": "SX-70 Model 2",
      "brand": "Polaroid",
      "model": "SX-70",
      "specific_model": "Model 2",
      "capacity": 10,
      "default_image": "camera.aperture",
      "default_icon": "camera.aperture",
      "year_introduced": 1975,
      "film_type": "SX-70"
    },
    {
      "id": "polaroid_sx70_model3",
      "name": "SX-70 Model 3",
      "brand": "Polaroid",
      "model": "SX-70",
      "specific_model": "Model 3",
      "capacity": 10,
      "default_image": "camera.aperture",
      "default_icon": "camera.aperture",
      "year_introduced": 1977,
      "film_type": "SX-70"
    },
    {
      "id": "polaroid_600",
      "name": "600",
      "brand": "Polaroid",
      "model": "600",
      "specific_model": "Original",
      "capacity": 8,
      "default_image": "camera.fill",
      "default_icon": "camera.fill",
      "year_introduced": 1981,
      "film_type": "600/i-Type"
    },
    {
      "id": "polaroid_600_onestep",
      "name": "600 OneStep",
      "brand": "Polaroid",
      "model": "600",
      "specific_model": "OneStep",
      "capacity": 8,
      "default_image": "camera.fill",
      "default_icon": "camera.fill",
      "year_introduced": 1983,
      "film_type": "600/i-Type"
    },
    {
      "id": "polaroid_600_express",
      "name": "600 Express",
      "brand": "Polaroid",
      "model": "600",
      "specific_model": "Express",
      "capacity": 8,
      "default_image": "camera.fill",
      "default_icon": "camera.fill",
      "year_introduced": 1984,
      "film_type": "600/i-Type"
    },
    {
      "id": "polaroid_600_autofocus",
      "name": "600 Autofocus",
      "brand": "Polaroid",
      "model": "600",
      "specific_model": "Autofocus",
      "capacity": 8,
      "default_image": "camera.fill",
      "default_icon": "camera.fill",
      "year_introduced": 1986,
      "film_type": "600/i-Type"
    },
    {
      "id": "polaroid_onestep2",
      "name": "OneStep 2",
      "brand": "Polaroid",
      "model": "OneStep",
      "specific_model": "2",
      "capacity": 8,
      "default_image": "camera.metering.unknown",
      "default_icon": "camera.metering.unknown",
      "year_introduced": 2017,
      "film_type": "i-Type"
    },
    {
      "id": "polaroid_onestep_plus",
      "name": "OneStep+",
      "brand": "Polaroid",
      "model": "OneStep",
      "specific_model": "+",
      "capacity": 8,
      "default_image": "camera.metering.spot",
      "default_icon": "camera.metering.spot",
      "year_introduced": 2018,
      "film_type": "i-Type"
    },
    {
      "id": "polaroid_now",
      "name": "Now",
      "brand": "Polaroid",
      "model": "Now",
      "specific_model": "Original",
      "capacity": 8,
      "default_image": "camera.metering.partial",
      "default_icon": "camera.metering.partial",
      "year_introduced": 2019,
      "film_type": "i-Type"
    },
    {
      "id": "polaroid_now_plus",
      "name": "Now+",
      "brand": "Polaroid",
      "model": "Now",
      "specific_model": "+",
      "capacity": 8,
      "default_image": "camera.metering.partial",
      "default_icon": "camera.metering.partial",
      "year_introduced": 2020,
      "film_type": "i-Type"
    },
    {
      "id": "polaroid_go",
      "name": "Go",
      "brand": "Polaroid",
      "model": "Go",
      "specific_model": "Original",
      "capacity": 8,
      "default_image": "camera.metering.none",
      "default_icon": "camera.metering.none",
      "year_introduced": 2021,
      "film_type": "i-Type"
    },
    {
      "id": "polaroid_i2",
      "name": "I-2",
      "brand": "Polaroid",
      "model": "I-2",
      "specific_model": "Original",
      "capacity": 8,
      "default_image": "camera.metering.center",
      "default_icon": "camera.metering.center",
      "year_introduced": 2023,
      "film_type": "i-Type/600/SX-70"
    },
    {
      "id": "polaroid_spectra",
      "name": "Spectra",
      "brand": "Polaroid",
      "model": "Spectra",
      "specific_model": "Original",
      "capacity": 10,
      "default_image": "camera.metering.center",
      "default_icon": "camera.metering.center",
      "year_introduced": 1986,
      "film_type": "Spectra"
    },
    {
      "id": "polaroid_8x10",
      "name": "8x10",
      "brand": "Polaroid",
      "model": "8x10",
      "specific_model": "Original",
      "capacity": 1,
      "default_image": "camera.metering.center",
      "default_icon": "camera.metering.center",
      "year_introduced": 1970,
      "film_type": "8x10"
    },
    {
      "id": "polaroid_4x5",
      "name": "4x5",
      "brand": "Polaroid",
      "model": "4x5",
      "specific_model": "Original",
      "capacity": 1,
      "default_image": "camera.metering.center",
      "default_icon": "camera.metering.center",
      "year_introduced": 1970,
      "film_type": "4x5"
    }
  ]
}
